solarenergy/__init__.py
solarenergy/radiation.py
solarenergy/solar_panels.py
solarenergy-0.1.11.dist-info/licenses/LICENCE
solarenergy-0.1.11.dist-info/METADATA
solarenergy-0.1.11.dist-info/WHEEL
solarenergy-0.1.11.dist-info/top_level.txt
solarenergy-0.1.11.dist-info/RECORD
