Metadata-Version: 2.4
Name: solarenergy
Version: 0.1.11
Summary: A Python module do simple modelling in the field of solar energy
Author-email: Marc van der Sluys <git@vandersluys.nl>
License-Expression: EUPL-1.2
Project-URL: GitHub, https://github.com/MarcvdSluys/SolarEnergy
Project-URL: ReadTheDocs, https://solarenergy.readthedocs.io
Keywords: solar energy,solar,energy,sun
Classifier: Development Status :: 4 - Beta
Classifier: Intended Audience :: Developers
Classifier: Intended Audience :: Education
Classifier: Intended Audience :: Science/Research
Classifier: Natural Language :: English
Classifier: Operating System :: OS Independent
Classifier: Programming Language :: Python :: 3
Classifier: Topic :: Scientific/Engineering
Classifier: Topic :: Scientific/Engineering :: Astronomy
Classifier: Topic :: Scientific/Engineering :: Physics
License-File: LICENCE
Requires-Dist: astroconst>=0.0.6
Requires-Dist: astrotool>=0.0.9
Requires-Dist: numpy
Requires-Dist: pytz
Requires-Dist: soltrack>=0.2.0
Dynamic: license-file
